[
  {
    "name": "sold_to_clients_table",
    "status": "ok",
    "site_path": "/sites/Einhell",
    "xlsx_path": "/Shared Documents/General/Einhell_internal/Остатки, товары в пути/Отгрузки клиентам_raw",
    "recursive": false,
    "files_total": 196,
    "files_xlsx": 196,
    "processed_xlsx": 196,
    "skipped_xlsx": 0,
    "used_fallback": 0,
    "unique_skus": 730,
    "runtime_s": 94.49
  },
  {
    "name": "transit_booked_table",
    "status": "ok",
    "site_path": "/sites/Einhell",
    "xlsx_path": "/Shared Documents/General/Einhell_internal/Остатки, товары в пути/Бронь в пути_raw",
    "recursive": false,
    "files_total": 6,
    "files_xlsx": 6,
    "processed_xlsx": 6,
    "skipped_xlsx": 0,
    "used_fallback": 0,
    "unique_skus": 178,
    "runtime_s": 3.74
  },
  {
    "name": "booked_table",
    "status": "ok",
    "site_path": "/sites/Einhell",
    "xlsx_path": "/Shared Documents/General/Einhell_internal/Остатки, товары в пути/Бронь клиентов_raw",
    "recursive": false,
    "files_total": 10,
    "files_xlsx": 10,
    "processed_xlsx": 10,
    "skipped_xlsx": 0,
    "used_fallback": 0,
    "unique_skus": 275,
    "runtime_s": 5.59
  },
  {
    "name": "demo_astana_table",
    "status": "ok",
    "site_path": "/sites/Einhell",
    "xlsx_path": "/Shared Documents/General/Einhell_internal/Остатки, товары в пути/Демофонд Астана_raw",
    "recursive": false,
    "files_total": 10,
    "files_xlsx": 10,
    "processed_xlsx": 10,
    "skipped_xlsx": 0,
    "used_fallback": 0,
    "unique_skus": 126,
    "runtime_s": 6.69
  },
  {
    "name": "demo_table",
    "status": "ok",
    "site_path": "/sites/Einhell",
    "xlsx_path": "/Shared Documents/General/Einhell_internal/Остатки, товары в пути/Демофонд_raw",
    "recursive": false,
    "files_total": 35,
    "files_xlsx": 35,
    "processed_xlsx": 35,
    "skipped_xlsx": 0,
    "used_fallback": 0,
    "unique_skus": 420,
    "runtime_s": 17.39
  },
  {
    "name": "service_table",
    "status": "ok",
    "site_path": "/sites/Einhell",
    "xlsx_path": "/Shared Documents/General/Einhell_internal/Остатки, товары в пути/Сервис_raw",
    "recursive": false,
    "files_total": 56,
    "files_xlsx": 56,
    "processed_xlsx": 56,
    "skipped_xlsx": 0,
    "used_fallback": 0,
    "unique_skus": 124,
    "runtime_s": 28.13
  },
  {
    "name": "inbound_table",
    "status": "ok",
    "site_path": "/sites/Einhell",
    "xlsx_path": "/Shared Documents/General/Einhell_internal/Остатки, товары в пути/Собственный товар на складе дистрибьютора_raw",
    "recursive": false,
    "files_total": 24,
    "files_xlsx": 24,
    "processed_xlsx": 24,
    "skipped_xlsx": 0,
    "used_fallback": 0,
    "unique_skus": 889,
    "runtime_s": 12.36
  },
  {
    "name": "sold_to_distr_table",
    "status": "ok",
    "site_path": "/sites/Einhell",
    "xlsx_path": "/Shared Documents/General/Einhell_internal/Остатки, товары в пути/Товар дистрибьютора_raw",
    "recursive": false,
    "files_total": 159,
    "files_xlsx": 159,
    "processed_xlsx": 159,
    "skipped_xlsx": 0,
    "used_fallback": 0,
    "unique_skus": 747,
    "runtime_s": 75.07
  },
  {
    "name": "spark_table",
    "status": "ok",
    "site_path": "/sites/Einhell",
    "xlsx_path": "/Shared Documents/General/Einhell_internal/Остатки, товары в пути/Товар на собственном складе_raw",
    "recursive": false,
    "files_total": 28,
    "files_xlsx": 28,
    "processed_xlsx": 28,
    "skipped_xlsx": 0,
    "used_fallback": 0,
    "unique_skus": 201,
    "runtime_s": 14.59
  },
  {
    "name": "in_transit_table",
    "status": "ok",
    "site_path": "/sites/Einhell",
    "xlsx_path": "/Shared Documents/General/Einhell_internal/Остатки, товары в пути/Товары в пути_raw",
    "recursive": false,
    "files_total": 2,
    "files_xlsx": 2,
    "processed_xlsx": 2,
    "skipped_xlsx": 0,
    "used_fallback": 0,
    "unique_skus": 54,
    "runtime_s": 2.07
  },
  {
    "name": "preorders_table",
    "status": "ok",
    "site_path": "/sites/Einhell",
    "xlsx_path": "/Shared Documents/General/Einhell_internal/Остатки, товары в пути/Предзаказы_raw",
    "recursive": false,
    "files_total": 3,
    "files_xlsx": 3,
    "processed_xlsx": 3,
    "skipped_xlsx": 0,
    "used_fallback": 0,
    "unique_skus": 143,
    "runtime_s": 2.95
  },
  {
    "name": "tref_table",
    "status": "ok",
    "site_path": "/sites/Einhell_common",
    "xlsx_path": "/Shared Documents/General/Маркетплейсы/Preorders/Preorders_raw",
    "recursive": false,
    "files_total": 249,
    "files_xlsx": 249,
    "processed_xlsx": 249,
    "skipped_xlsx": 0,
    "used_fallback": 0,
    "unique_skus": 261,
    "runtime_s": 161.57
  }
]